repo_loader/.gptignore
repo_loader/__init__.py
repo_loader/cli.py
repo_loader/repo_loader.py
repo_loader/utils.py
repo_loader-0.2.3.dist-info/LICENSE
repo_loader-0.2.3.dist-info/METADATA
repo_loader-0.2.3.dist-info/WHEEL
repo_loader-0.2.3.dist-info/entry_points.txt
repo_loader-0.2.3.dist-info/top_level.txt
repo_loader-0.2.3.dist-info/RECORD
