Metadata-Version: 2.1
Name: repo-loader
Version: 0.2.3
Summary: repository loader for github and chatgpt
Home-page: https://github.com/cachho/repo-loader
Maintainer: cachho
License: BSD 3-Clause License
Keywords: template-python-cmd
Classifier: Programming Language :: Python :: 3
Requires-Python: >=3.7
License-File: LICENSE
Requires-Dist: pyperclip
Requires-Dist: pathspec ==0.11.1
Requires-Dist: tqdm ==4.65.0
